py_api_decorators/__init__.py
py_api_decorators/json.py
py_api_decorators-0.1.0.dist-info/LICENSE
py_api_decorators-0.1.0.dist-info/METADATA
py_api_decorators-0.1.0.dist-info/WHEEL
py_api_decorators-0.1.0.dist-info/top_level.txt
py_api_decorators-0.1.0.dist-info/RECORD
